jupytex/__init__.py
jupytex/__main__.py
jupytex/interface.py
jupytex/tools.py
jupytex/data/.latexmkrc
jupytex/data/__init__.py
jupytex/data/jupytex.sty
jupytex-0.0.3.dist-info/LICENSE.md
jupytex-0.0.3.dist-info/METADATA
jupytex-0.0.3.dist-info/WHEEL
jupytex-0.0.3.dist-info/entry_points.txt
jupytex-0.0.3.dist-info/top_level.txt
jupytex-0.0.3.dist-info/RECORD
