Metadata-Version: 2.1
Name: jupytex
Version: 0.0.3
Summary: Jupyter execution of TeX code environments.
Home-page: https://github.com/agoose77/jupytex
Author: Angus Hollands
Author-email: goosey15@gmail.com
License: UNKNOWN
Platform: UNKNOWN
Classifier: Programming Language :: Python :: 3.6
Classifier: Programming Language :: Python :: 3.7
Classifier: Framework :: Jupyter
Classifier: Development Status :: 3 - Alpha
Classifier: License :: OSI Approved :: MIT License
Classifier: Operating System :: OS Independent
Classifier: Topic :: Text Processing :: Markup :: LaTeX
Requires-Python: >=3.6
Requires-Dist: colorama
Requires-Dist: jupyter-client
Requires-Dist: jupyter
Requires-Dist: importlib-resources
